todo/__init__.py
todo/checker.py
todo/plugin.py
pytest_todo-0.2.1.dist-info/LICENSE
pytest_todo-0.2.1.dist-info/METADATA
pytest_todo-0.2.1.dist-info/WHEEL
pytest_todo-0.2.1.dist-info/entry_points.txt
pytest_todo-0.2.1.dist-info/top_level.txt
pytest_todo-0.2.1.dist-info/RECORD
