Metadata-Version: 2.1
Name: pytest-todo
Version: 0.2.1
Summary: A small plugin for the pytest testing framework, marking TODO comments as failure
Home-page: https://github.com/TobiasPleyer/pytest-todo
Author: Tobias Pleyer
Author-email: tobi.pleyer@gmail.com
License: MIT
Platform: UNKNOWN
Classifier: Development Status :: 4 - Beta
Classifier: Framework :: Pytest
Classifier: Intended Audience :: Developers
Classifier: License :: OSI Approved :: MIT License
Classifier: Programming Language :: Python
Classifier: Programming Language :: Python :: 2
Classifier: Programming Language :: Python :: 3
Classifier: Topic :: Software Development :: Testing
Requires-Dist: pytest
